{
  "original": "manufactured you passionately reflect a This",
  "candidate": "manufactured you passionately reflect a This.",
  "selected": "manufactured you passionately reflect a This.",
  "accepted": true,
  "reason": "accepted_deterministic",
  "original_score": 0.87,
  "candidate_score": 0.92,
  "original_pressure": 0.366,
  "candidate_pressure": 0.296,
  "pressure_relief": 0.07,
  "safe": true,
  "metadata": {
    "prompt_excerpt": "He did, did you know he was afraid of bambi that is really funny",
    "input_interpretation": {
      "raw_prompt": "He did, did you know he was afraid of bambi that is really funny",
      "intent_hint": "statement_or_context",
      "topic_terms": [
        "know",
        "afraid",
        "bambi",
        "really",
        "funny"
      ],
      "entities": []
    },
    "tone": "playful",
    "source": "deterministic",
    "timestamp": 1778989183.0906625,
    "min_relief_used": 0.035
  }
}