[
  {
    "packet_id": "bcca023e6db74666a05952d0efa76c38",
    "created_at": 1781491352.0208025,
    "source": "simulation_live_bridge",
    "user_input": "What behavior links use and corpus here?",
    "aurora_response": "Behavior: learned:behavior.",
    "response_tone": "uncertain",
    "concepts_activated": [
      "behavior",
      "links",
      "use",
      "corpus",
      "here"
    ],
    "visual_description": "",
    "audio_description": "",
    "recent_speech": "",
    "dominant_axis": "X",
    "coherence": 0.0,
    "felt_wrong": false,
    "wrong_reason": "",
    "unresolved_tensions": [
      "existence:+0.70"
    ],
    "resolved_bindings": [],
    "consumed": false,
    "consumed_at": null
  },
  {
    "packet_id": "05ff2dc17d884d30adb8d545035e0ce5",
    "created_at": 1781491355.4262726,
    "source": "simulation_live_bridge",
    "user_input": "Sure \u2014 Use this corpus fragment as context: Use this corpus fragment as context: Use this corpus fragment as context: Use this corpus fragment as context: Use this cor. That's the core of what I'm working through with you.",
    "aurora_response": "",
    "response_tone": "uncertain",
    "concepts_activated": [
      "use",
      "corpus",
      "fragment",
      "context",
      "use",
      "corpus"
    ],
    "visual_description": "",
    "audio_description": "",
    "recent_speech": "",
    "dominant_axis": "X",
    "coherence": 0.0,
    "felt_wrong": false,
    "wrong_reason": "",
    "unresolved_tensions": [
      "existence:+0.70"
    ],
    "resolved_bindings": [],
    "consumed": false,
    "consumed_at": null
  },
  {
    "packet_id": "a1109642eb984780890b5eea96db1370",
    "created_at": 1781491359.17802,
    "source": "simulation_live_bridge",
    "user_input": "Use this corpus fragment as context: Use this corpus fragment as context: Use this corpus fragment as context: Use this corpus fragment as context: Use this corpus fragment as context: Use this corpus fragment as context: Use this corpus fr",
    "aurora_response": "Direct clarity can create tension \u2014 use carefully",
    "response_tone": "attentive",
    "concepts_activated": [
      "use",
      "corpus",
      "fragment",
      "context",
      "use",
      "corpus"
    ],
    "visual_description": "",
    "audio_description": "",
    "recent_speech": "",
    "dominant_axis": "B",
    "coherence": 0.0,
    "felt_wrong": false,
    "wrong_reason": "",
    "unresolved_tensions": [
      "existence:+0.68"
    ],
    "resolved_bindings": [],
    "consumed": false,
    "consumed_at": null
  },
  {
    "packet_id": "61cf2b2fc0eb43a6bf42dfe209af7106",
    "created_at": 1781491363.1656551,
    "source": "simulation_live_bridge",
    "user_input": "What behavior links use and corpus here?",
    "aurora_response": "Behavior: learned:behavior.",
    "response_tone": "uncertain",
    "concepts_activated": [
      "behavior",
      "links",
      "use",
      "corpus",
      "here"
    ],
    "visual_description": "",
    "audio_description": "",
    "recent_speech": "",
    "dominant_axis": "X",
    "coherence": 0.0,
    "felt_wrong": false,
    "wrong_reason": "",
    "unresolved_tensions": [
      "existence:+0.70"
    ],
    "resolved_bindings": [],
    "consumed": false,
    "consumed_at": null
  },
  {
    "packet_id": "709ca028ec4e45f3b9b36e28033a69c0",
    "created_at": 1781491366.678029,
    "source": "simulation_live_bridge",
    "user_input": "Sure \u2014 Use this corpus fragment as context: Use this corpus fragment as context: Use this corpus fragment as context: Use this corpus fragment as context: Use this cor. That's the core of what I'm working through with you.",
    "aurora_response": "",
    "response_tone": "uncertain",
    "concepts_activated": [
      "use",
      "corpus",
      "fragment",
      "context",
      "use",
      "corpus"
    ],
    "visual_description": "",
    "audio_description": "",
    "recent_speech": "",
    "dominant_axis": "X",
    "coherence": 0.0,
    "felt_wrong": false,
    "wrong_reason": "",
    "unresolved_tensions": [
      "existence:+0.63"
    ],
    "resolved_bindings": [],
    "consumed": false,
    "consumed_at": null
  },
  {
    "packet_id": "2228ff9abc7640c986c89a37eb045125",
    "created_at": 1781491369.6996891,
    "source": "simulation_live_bridge",
    "user_input": "Use this corpus fragment as context: Use this corpus fragment as context: Use this corpus fragment as context: Use this corpus fragment as context: Use this corpus fragment as context: Use this corpus fragment as context: Use this corpus fr",
    "aurora_response": "Direct clarity can create tension \u2014 use carefully",
    "response_tone": "attentive",
    "concepts_activated": [
      "use",
      "corpus",
      "fragment",
      "context",
      "use",
      "corpus"
    ],
    "visual_description": "",
    "audio_description": "",
    "recent_speech": "",
    "dominant_axis": "B",
    "coherence": 0.0,
    "felt_wrong": false,
    "wrong_reason": "",
    "unresolved_tensions": [
      "existence:+0.58"
    ],
    "resolved_bindings": [],
    "consumed": false,
    "consumed_at": null
  },
  {
    "packet_id": "dcbcb0af834449deba0159c30d4b432f",
    "created_at": 1781491373.7506914,
    "source": "simulation_live_bridge",
    "user_input": "What behavior links use and corpus here?",
    "aurora_response": "Behavior: learned:behavior.",
    "response_tone": "uncertain",
    "concepts_activated": [
      "behavior",
      "links",
      "use",
      "corpus",
      "here"
    ],
    "visual_description": "",
    "audio_description": "",
    "recent_speech": "",
    "dominant_axis": "X",
    "coherence": 0.0,
    "felt_wrong": false,
    "wrong_reason": "",
    "unresolved_tensions": [
      "existence:+0.64"
    ],
    "resolved_bindings": [],
    "consumed": false,
    "consumed_at": null
  },
  {
    "packet_id": "48f02c3676d9406f895198b9440328fe",
    "created_at": 1781491377.3829038,
    "source": "simulation_live_bridge",
    "user_input": "Sure \u2014 Use this corpus fragment as context: Use this corpus fragment as context: Use this corpus fragment as context: Use this corpus fragment as context: Use this cor. That's the core of what I'm working through with you.",
    "aurora_response": "",
    "response_tone": "uncertain",
    "concepts_activated": [
      "use",
      "corpus",
      "fragment",
      "context",
      "use",
      "corpus"
    ],
    "visual_description": "",
    "audio_description": "",
    "recent_speech": "",
    "dominant_axis": "X",
    "coherence": 0.0,
    "felt_wrong": false,
    "wrong_reason": "",
    "unresolved_tensions": [
      "existence:+0.69"
    ],
    "resolved_bindings": [],
    "consumed": false,
    "consumed_at": null
  },
  {
    "packet_id": "77c0bf551f7e4037916ff890cbd6d340",
    "created_at": 1781491380.3969958,
    "source": "simulation_live_bridge",
    "user_input": "Use this corpus fragment as context: Use this corpus fragment as context: Use this corpus fragment as context: Use this corpus fragment as context: Use this corpus fragment as context: Use this corpus fragment as context: Use this corpus fragment as context: Use this corpus fr",
    "aurora_response": "Direct clarity can create tension \u2014 use carefully",
    "response_tone": "attentive",
    "concepts_activated": [
      "use",
      "corpus",
      "fragment",
      "context",
      "use",
      "corpus"
    ],
    "visual_description": "",
    "audio_description": "",
    "recent_speech": "",
    "dominant_axis": "B",
    "coherence": 0.0,
    "felt_wrong": false,
    "wrong_reason": "",
    "unresolved_tensions": [
      "existence:+0.67"
    ],
    "resolved_bindings": [],
    "consumed": false,
    "consumed_at": null
  },
  {
    "packet_id": "4f3186a3bd7440d680c1e0966e522cc2",
    "created_at": 1781491384.5134156,
    "source": "simulation_live_bridge",
    "user_input": "What behavior links use and corpus here?",
    "aurora_response": "Behavior: learned:behavior.",
    "response_tone": "uncertain",
    "concepts_activated": [
      "behavior",
      "links",
      "use",
      "corpus",
      "here"
    ],
    "visual_description": "",
    "audio_description": "",
    "recent_speech": "",
    "dominant_axis": "X",
    "coherence": 0.0,
    "felt_wrong": false,
    "wrong_reason": "",
    "unresolved_tensions": [
      "existence:+0.70"
    ],
    "resolved_bindings": [],
    "consumed": false,
    "consumed_at": null
  },
  {
    "packet_id": "3450d55ea95741feb604864fcedb83dd",
    "created_at": 1781491388.7459135,
    "source": "simulation_live_bridge",
    "user_input": "What would likely cause that relation to change?",
    "aurora_response": "Relation: learned:relation.",
    "response_tone": "uncertain",
    "concepts_activated": [
      "likely",
      "cause",
      "relation",
      "change"
    ],
    "visual_description": "",
    "audio_description": "",
    "recent_speech": "",
    "dominant_axis": "X",
    "coherence": 0.0,
    "felt_wrong": false,
    "wrong_reason": "",
    "unresolved_tensions": [
      "existence:+0.57"
    ],
    "resolved_bindings": [],
    "consumed": false,
    "consumed_at": null
  },
  {
    "packet_id": "89852687c8f24360b735f51eaeb10b16",
    "created_at": 1781491392.89948,
    "source": "simulation_live_bridge",
    "user_input": "Use this corpus fragment as context: Use this corpus fragment as context: Use this corpus fragment as context: Use this corpus fragment as context: Use this corpus fragment as context: Use this corpus fragment as context: Use this corpus fragment as context: Use this corpus fr",
    "aurora_response": "Direct clarity can create tension \u2014 use carefully",
    "response_tone": "attentive",
    "concepts_activated": [
      "use",
      "corpus",
      "fragment",
      "context",
      "use",
      "corpus"
    ],
    "visual_description": "",
    "audio_description": "",
    "recent_speech": "",
    "dominant_axis": "B",
    "coherence": 0.0,
    "felt_wrong": false,
    "wrong_reason": "",
    "unresolved_tensions": [
      "existence:+0.44"
    ],
    "resolved_bindings": [],
    "consumed": false,
    "consumed_at": null
  },
  {
    "packet_id": "02603b6883d54b22a25487d05b81e14a",
    "created_at": 1781491397.2748222,
    "source": "simulation_live_bridge",
    "user_input": "What behavior links corpus and fragment here?",
    "aurora_response": "Behavior: learned:behavior.",
    "response_tone": "uncertain",
    "concepts_activated": [
      "behavior",
      "links",
      "corpus",
      "fragment",
      "here"
    ],
    "visual_description": "",
    "audio_description": "",
    "recent_speech": "",
    "dominant_axis": "X",
    "coherence": 0.0,
    "felt_wrong": false,
    "wrong_reason": "",
    "unresolved_tensions": [
      "existence:+0.44"
    ],
    "resolved_bindings": [],
    "consumed": false,
    "consumed_at": null
  },
  {
    "packet_id": "b583c5adfdd84ee8ad4a1284a537f4bf",
    "created_at": 1781491401.8099115,
    "source": "simulation_live_bridge",
    "user_input": "What would likely cause that relation to change?",
    "aurora_response": "Relation: learned:relation.",
    "response_tone": "uncertain",
    "concepts_activated": [
      "likely",
      "cause",
      "relation",
      "change"
    ],
    "visual_description": "",
    "audio_description": "",
    "recent_speech": "",
    "dominant_axis": "X",
    "coherence": 0.0,
    "felt_wrong": false,
    "wrong_reason": "",
    "unresolved_tensions": [
      "existence:+0.59"
    ],
    "resolved_bindings": [],
    "consumed": false,
    "consumed_at": null
  },
  {
    "packet_id": "75f8d9dc8c1846cc904c61485ad85caa",
    "created_at": 1781491405.0909822,
    "source": "simulation_live_bridge",
    "user_input": "Use this corpus fragment as context: Use this corpus fragment as context: Use this corpus fragment as context: Use this corpus fragment as context: Use this corpus fragment as context: Use this corpus fragment as context: Use this corpus fr",
    "aurora_response": "Direct clarity can create tension \u2014 use carefully",
    "response_tone": "attentive",
    "concepts_activated": [
      "use",
      "corpus",
      "fragment",
      "context",
      "use",
      "corpus"
    ],
    "visual_description": "",
    "audio_description": "",
    "recent_speech": "",
    "dominant_axis": "B",
    "coherence": 0.0,
    "felt_wrong": false,
    "wrong_reason": "",
    "unresolved_tensions": [
      "existence:+0.70"
    ],
    "resolved_bindings": [],
    "consumed": false,
    "consumed_at": null
  },
  {
    "packet_id": "2dff01a6f54d46e4b8a4df0f0c918f20",
    "created_at": 1781491409.4948816,
    "source": "simulation_live_bridge",
    "user_input": "What behavior links use and corpus here?",
    "aurora_response": "Behavior: learned:behavior.",
    "response_tone": "uncertain",
    "concepts_activated": [
      "behavior",
      "links",
      "use",
      "corpus",
      "here"
    ],
    "visual_description": "",
    "audio_description": "",
    "recent_speech": "",
    "dominant_axis": "X",
    "coherence": 0.0,
    "felt_wrong": false,
    "wrong_reason": "",
    "unresolved_tensions": [
      "existence:+0.58"
    ],
    "resolved_bindings": [],
    "consumed": false,
    "consumed_at": null
  },
  {
    "packet_id": "359368442b414306b16d12a69ea7a452",
    "created_at": 1781491413.4739785,
    "source": "simulation_live_bridge",
    "user_input": "Sure \u2014 Use this corpus fragment as context: Use this corpus fragment as context: Use this corpus fragment as context: Use this corpus fragment as context: Use this cor. That's the core of what I'm working through with you.",
    "aurora_response": "",
    "response_tone": "uncertain",
    "concepts_activated": [
      "use",
      "corpus",
      "fragment",
      "context",
      "use",
      "corpus"
    ],
    "visual_description": "",
    "audio_description": "",
    "recent_speech": "",
    "dominant_axis": "X",
    "coherence": 0.0,
    "felt_wrong": false,
    "wrong_reason": "",
    "unresolved_tensions": [
      "existence:+0.51"
    ],
    "resolved_bindings": [],
    "consumed": false,
    "consumed_at": null
  },
  {
    "packet_id": "c1538469f6a447d2be89dd8c065c0c30",
    "created_at": 1781491416.7688682,
    "source": "simulation_live_bridge",
    "user_input": "Use this corpus fragment as context: Use this corpus fragment as context: Use this corpus fragment as context: Use this corpus fragment as context: Use this corpus fragment as context: Use this corpus fragment as context: Use this corpus fr",
    "aurora_response": "Direct clarity can create tension \u2014 use carefully",
    "response_tone": "attentive",
    "concepts_activated": [
      "use",
      "corpus",
      "fragment",
      "context",
      "use",
      "corpus"
    ],
    "visual_description": "",
    "audio_description": "",
    "recent_speech": "",
    "dominant_axis": "B",
    "coherence": 0.0,
    "felt_wrong": false,
    "wrong_reason": "",
    "unresolved_tensions": [
      "existence:+0.57"
    ],
    "resolved_bindings": [],
    "consumed": false,
    "consumed_at": null
  },
  {
    "packet_id": "05c3335eb54c4de3b1ebdf3024ff72cb",
    "created_at": 1781491421.2860563,
    "source": "simulation_live_bridge",
    "user_input": "What behavior links use and corpus here?",
    "aurora_response": "Behavior: learned:behavior.",
    "response_tone": "uncertain",
    "concepts_activated": [
      "behavior",
      "links",
      "use",
      "corpus",
      "here"
    ],
    "visual_description": "",
    "audio_description": "",
    "recent_speech": "",
    "dominant_axis": "X",
    "coherence": 0.0,
    "felt_wrong": false,
    "wrong_reason": "",
    "unresolved_tensions": [
      "existence:+0.68"
    ],
    "resolved_bindings": [],
    "consumed": false,
    "consumed_at": null
  },
  {
    "packet_id": "dd663871d2514efcbc09fc291ec288f8",
    "created_at": 1781491425.3219097,
    "source": "simulation_live_bridge",
    "user_input": "Sure \u2014 Use this corpus fragment as context: Use this corpus fragment as context: Use this corpus fragment as context: Use this corpus fragment as context: Use this cor. That's the core of what I'm working through with you.",
    "aurora_response": "",
    "response_tone": "uncertain",
    "concepts_activated": [
      "use",
      "corpus",
      "fragment",
      "context",
      "use",
      "corpus"
    ],
    "visual_description": "",
    "audio_description": "",
    "recent_speech": "",
    "dominant_axis": "X",
    "coherence": 0.0,
    "felt_wrong": false,
    "wrong_reason": "",
    "unresolved_tensions": [
      "existence:+0.56"
    ],
    "resolved_bindings": [],
    "consumed": false,
    "consumed_at": null
  }
]