{
  "node_id": "b08912e4-ba62-44ab-aa0e-fe06071854d1",
  "order": "COMPOSITE",
  "payload": {
    "target": "aurora.dialogue.self_repair",
    "issue": "coherence_maintenance",
    "logic_tier": "runtime_orchestration",
    "intervention": "active_self_repair_orientation",
    "intended_effect": "turn low coherence into focused repair and learning pressure",
    "observed_effect": "resolved_partially",
    "recurrence_pattern": "periodic__single_target",
    "distribution_context": "single_module__isolated"
  },
  "point_scores": {
    "target__issue": 0.7,
    "issue__logic_tier": 0.7,
    "logic_tier__intervention": 0.7,
    "intervention__intended_effect": 0.7,
    "intended_effect__observed_effect": 0.5,
    "observed_effect__issue": 0.5,
    "target__logic_tier": 0.7,
    "target__intervention": 0.2,
    "issue__intervention": 0.7,
    "issue__intended_effect": 0.7,
    "logic_tier__observed_effect": 0.7,
    "target__observed_effect": 0.7,
    "issue__recurrence_pattern": 0.5,
    "target__recurrence_pattern": 0.45,
    "logic_tier__recurrence_pattern": 0.425,
    "intervention__recurrence_pattern": 0.4,
    "target__distribution_context": 0.2,
    "issue__distribution_context": 0.2,
    "logic_tier__distribution_context": 0.2,
    "observed_effect__distribution_context": 0.18000000000000002
  },
  "resolution_fidelity": 0.5,
  "base_event_ids": [
    "26e6f29d-5eca-4dbb-a660-4ba6dbe04999",
    "d40e272b-93e5-4990-b43c-051fcccbc754",
    "eb86b92b-8f60-4219-b5c8-a4d1f2b1e1e2",
    "71a01ff6-12fb-4d06-9774-c336774ae2b9",
    "9e037d8f-f7e3-4c9a-90c9-5c35cdf4c930"
  ],
  "parent_ids": [
    "26e6f29d-5eca-4dbb-a660-4ba6dbe04999",
    "d40e272b-93e5-4990-b43c-051fcccbc754",
    "eb86b92b-8f60-4219-b5c8-a4d1f2b1e1e2",
    "71a01ff6-12fb-4d06-9774-c336774ae2b9",
    "9e037d8f-f7e3-4c9a-90c9-5c35cdf4c930"
  ],
  "child_ids": [],
  "tags": [
    "dialogue",
    "runtime",
    "self_repair",
    "learning",
    "phase:runtime_dialogue",
    "coherence",
    "composite",
    "ghost_relic_rehydrated"
  ],
  "quasi_strata": null,
  "rotation_history": [],
  "lineage_meta": {
    "ghost_relic_id": "relic::composite::1366a5d7_a2c3_4373_9bd6_05a240f0308f",
    "ghost_relic_match": 1.0,
    "family_key": "issue_family::coherence_maintenance",
    "issue_category": "coherence_maintenance",
    "stage": "COMPOSITE",
    "version": 28,
    "signature": "8df966c5313b777ecd6f",
    "is_active_version": false,
    "supersedes": "c84a1dad-b703-4a66-b2a2-315cd2a64d47",
    "superseded_by": "a08390fd-32a8-4c79-b82a-0e381efda664"
  },
  "created_at": "2026-03-30T00:19:16.470560+00:00",
  "persisted_at": "2026-03-30T00:21:28.945539+00:00",
  "is_relic": false,
  "checksum": "6eee44905174104e"
}