{
  "node_id": "eb4454d9-498c-4e20-92c5-ab379702e7ab",
  "order": "COMPOSITE",
  "payload": {
    "target": "aurora.dialogue.self_repair",
    "issue": "coherence_maintenance",
    "logic_tier": "runtime_orchestration",
    "intervention": "active_self_repair_orientation",
    "intended_effect": "turn low coherence into focused repair and learning pressure",
    "observed_effect": "resolved_partially",
    "recurrence_pattern": "sporadic__single_target",
    "distribution_context": "single_module__isolated"
  },
  "point_scores": {
    "target__issue": 0.7,
    "issue__logic_tier": 0.7,
    "logic_tier__intervention": 0.7,
    "intervention__intended_effect": 0.7,
    "intended_effect__observed_effect": 0.5,
    "observed_effect__issue": 0.5,
    "target__logic_tier": 0.7,
    "target__intervention": 0.2,
    "issue__intervention": 0.7,
    "issue__intended_effect": 0.7,
    "logic_tier__observed_effect": 0.7,
    "target__observed_effect": 0.7,
    "issue__recurrence_pattern": 0.36124999999999996,
    "target__recurrence_pattern": 0.325125,
    "logic_tier__recurrence_pattern": 0.30706249999999996,
    "intervention__recurrence_pattern": 0.28900000000000003,
    "target__distribution_context": 0.2,
    "issue__distribution_context": 0.2,
    "logic_tier__distribution_context": 0.2,
    "observed_effect__distribution_context": 0.18000000000000002
  },
  "resolution_fidelity": 0.5,
  "base_event_ids": [
    "ceca1fb0-ab25-4e0f-b46c-08f212b70870",
    "39b8f53b-b329-44e9-9450-99f3c156add0",
    "3fbf7de0-3fe5-4bf5-b9ee-ce7aef84ab89"
  ],
  "parent_ids": [
    "ceca1fb0-ab25-4e0f-b46c-08f212b70870",
    "39b8f53b-b329-44e9-9450-99f3c156add0",
    "3fbf7de0-3fe5-4bf5-b9ee-ce7aef84ab89"
  ],
  "child_ids": [],
  "tags": [
    "learning",
    "runtime",
    "coherence",
    "self_repair",
    "phase:runtime_dialogue",
    "dialogue",
    "composite",
    "ghost_relic_rehydrated"
  ],
  "quasi_strata": null,
  "rotation_history": [],
  "lineage_meta": {
    "ghost_relic_id": "relic::composite::64fbf5cb_d7b1_421c_8834_5937399cd1fd",
    "ghost_relic_match": 0.9375,
    "family_key": "issue_family::coherence_maintenance",
    "issue_category": "coherence_maintenance",
    "stage": "COMPOSITE",
    "version": 182,
    "signature": "9ce38ea9ac36b4d7f4a7",
    "is_active_version": false,
    "supersedes": "959cd114-89cf-4f18-815a-1cb3d58aa710",
    "superseded_by": "e86bc287-d27d-4371-bc90-c00681422a7f"
  },
  "created_at": "2026-05-03T07:24:02.968923+00:00",
  "persisted_at": "2026-05-03T07:34:37.489839+00:00",
  "is_relic": false,
  "checksum": "386fb7b7a5fee6c8"
}